lfd/__init__.py
lfd/analysis/__init__.py
lfd/analysis/utils.py
lfd/analysis/plotting/__init__.py
lfd/analysis/plotting/paperplots.py
lfd/analysis/plotting/utils.py
lfd/analysis/plotting/data/lsst_disk_data.npy
lfd/analysis/plotting/data/lsst_point_data.npy
lfd/analysis/plotting/data/lsst_radii_data.npy
lfd/analysis/plotting/data/paperstyle.mplstyle
lfd/analysis/plotting/data/sdss_disk_data.npy
lfd/analysis/plotting/data/sdss_point_data.npy
lfd/analysis/plotting/data/sdss_radii_data.npy
lfd/analysis/plotting/data/bckup/lsst_diskeq_data.npy
lfd/analysis/plotting/data/bckup/lsst_diskgg_data.npy
lfd/analysis/plotting/data/bckup/lsst_point_data.npy
lfd/analysis/plotting/data/bckup/lsst_radii_data.npy
lfd/analysis/plotting/data/bckup/paperstyle.mplstyle
lfd/analysis/plotting/data/bckup/sdss_diskeq_data.npy
lfd/analysis/plotting/data/bckup/sdss_diskgg_data.npy
lfd/analysis/plotting/data/bckup/sdss_point_data.npy
lfd/analysis/plotting/data/bckup/sdss_radii_data.npy
lfd/analysis/profiles/__init__.py
lfd/analysis/profiles/consts.py
lfd/analysis/profiles/convolution.py
lfd/analysis/profiles/convolutionobj.py
lfd/analysis/profiles/defocusing.py
lfd/analysis/profiles/objectprofiles.py
lfd/analysis/profiles/samplers.py
lfd/analysis/profiles/seeing.py
lfd/analysis/profiles/utils.py
lfd/analysis/profiles/data/gen_rabina_profile.py
lfd/analysis/profiles/data/lfd_rabina0_r.png
lfd/analysis/profiles/data/lfd_rabina10_r.png
lfd/analysis/profiles/data/lfd_rabina11_r.png
lfd/analysis/profiles/data/lfd_rabina12_r.png
lfd/analysis/profiles/data/lfd_rabina13_r.png
lfd/analysis/profiles/data/lfd_rabina14_r.png
lfd/analysis/profiles/data/lfd_rabina15_r.png
lfd/analysis/profiles/data/lfd_rabina1_r.png
lfd/analysis/profiles/data/lfd_rabina2_r.png
lfd/analysis/profiles/data/lfd_rabina3_r.png
lfd/analysis/profiles/data/lfd_rabina4_r.png
lfd/analysis/profiles/data/lfd_rabina5_r.png
lfd/analysis/profiles/data/lfd_rabina6_r.png
lfd/analysis/profiles/data/lfd_rabina7_r.png
lfd-2.0.0.dist-info/LICENSE
lfd-2.0.0.dist-info/METADATA
lfd-2.0.0.dist-info/WHEEL
lfd-2.0.0.dist-info/top_level.txt
lfd-2.0.0.dist-info/RECORD
